appointment_workflow_manager/__init__.py
appointment_workflow_manager/audit_logger.py
appointment_workflow_manager/conflict_checker.py
appointment_workflow_manager/workflow_manager.py
appointment_workflow_manager-0.2.1.dist-info/LICENSE
appointment_workflow_manager-0.2.1.dist-info/METADATA
appointment_workflow_manager-0.2.1.dist-info/WHEEL
appointment_workflow_manager-0.2.1.dist-info/top_level.txt
appointment_workflow_manager-0.2.1.dist-info/RECORD
