Metadata-Version: 2.1
Name: appointment-workflow-manager
Version: 0.2.1
Summary: Utilities to manage appointment workflows including approval, rejection, cancellation, audit logging, and conflict detection.
Home-page: https://github.com/yourusername/appointment-workflow-manager
Author: Vinay Gunda
Author-email: x23302712@student.ncirl.ie
License: MIT
Classifier: Programming Language :: Python :: 3
Classifier: Framework :: Django
Classifier: License :: OSI Approved :: MIT License
Classifier: Operating System :: OS Independent
Requires-Python: >=3.6
License-File: LICENSE
Requires-Dist: Django >=3.2
